Workbook

Sheet Assumptions
A1: AP Three-Way Match — Audit Assumptions
A3: Operational
A4: Annual invoice volume | B4: 120000 | C4: Mid-market manufacturer (~10k/mo)
A5: Avg manual handle time (min/invoice) | B5: 9 | C5: Discovery interview input
A6: Loaded AP cost ($/hour) | B6: 35 | C6: From client FP&A
A7: Loaded AP cost ($/min) | B7: =B6/60 -> 0.58333333
A8: Clean / auto-payable share | B8: 0.811 | C8: Sandbox: harness/results.json
A9: Exception share | B9: =1-B8 -> 0.189
A10: Hybrid review time (min/flagged item) | B10: 4
A11: Spot-QA time on clean (min/invoice) | B11: 0.5
A13: Risk
A14: Fraud rate (% of volume) | B14: 0.012 | C14: Sandbox label rate
A15: Residual fraud miss rate if FULLY automated | B15: 0.5 | C15: Sandbox fraud recall gap
A16: Avg net loss per missed fraud ($) | B16: 4500 | C16: Client risk team estimate
A17: Duplicate rate (% of volume) | B17: 0.029
A18: Manual duplicate miss rate (today) | B18: 0.3 | C18: Humans miss dupes in manual flow
A19: Net loss per missed duplicate ($) | B19: 900
A21: Upside
A22: Avg invoice value ($) | B22: 1800
A23: Early-pay discount available (%) | B23: 0.02
A24: Current discount capture rate | B24: 0.4
A25: Target discount capture rate | B25: 0.85
A27: Cost to run (annual)
A28: Software / platform | B28: 60000
A29: Implementation (amortized) | B29: 40000
A30: Oversight / governance | B30: 50000

Sheet Workflow Audit
A1: Sub-workflow scoring — impact x risk -> decision
A3: Sub-workflow | B3: Impact | C3: Risk | D3: Decision | E3: Rationale
A4: Invoice data capture (OCR/extract) | B4: 4 | C4: 2 | D4: =IF(B4<3,"Manual/Kill",IF(AND(B4>=4,C4>=4),"Hybrid",IF(AND(B4>=4,C4<=3),"Automate","Hybrid"))) -> Automate | E4: Deterministic; reversible before posting
A5: Three-way match (clean invoices) | B5: 5 | C5: 2 | D5: =IF(B5<3,"Manual/Kill",IF(AND(B5>=4,C5>=4),"Hybrid",IF(AND(B5>=4,C5<=3),"Automate","Hybrid"))) -> Automate | E5: 81% of volume; high accuracy in sandbox
A6: Duplicate detection / auto-hold | B6: 4 | C6: 2 | D6: =IF(B6<3,"Manual/Kill",IF(AND(B6>=4,C6>=4),"Hybrid",IF(AND(B6>=4,C6<=3),"Automate","Hybrid"))) -> Automate | E6: 100% recall; catches dupes humans miss
A7: Price / quantity mismatch resolution | B7: 4 | C7: 3 | D7: =IF(B7<3,"Manual/Kill",IF(AND(B7>=4,C7>=4),"Hybrid",IF(AND(B7>=4,C7<=3),"Automate","Hybrid"))) -> Automate | E7: Needs judgment on tolerance + vendor comms
A8: Missing-PO / non-PO routing | B8: 3 | C8: 3 | D8: =IF(B8<3,"Manual/Kill",IF(AND(B8>=4,C8>=4),"Hybrid",IF(AND(B8>=4,C8<=3),"Automate","Hybrid"))) -> Hybrid | E8: Policy-dependent; route to owner
A9: Tax / GL coding | B9: 3 | C9: 3 | D9: =IF(B9<3,"Manual/Kill",IF(AND(B9>=4,C9>=4),"Hybrid",IF(AND(B9>=4,C9<=3),"Automate","Hybrid"))) -> Hybrid | E9: Automatable with periodic sampling
A10: Fraud / bank-change screening | B10: 5 | C10: 5 | D10: =IF(B10<3,"Manual/Kill",IF(AND(B10>=4,C10>=4),"Hybrid",IF(AND(B10>=4,C10<=3),"Automate","Hybrid"))) -> Hybrid | E10: Sandbox missed 50% of fraud; irreversible
A11: Payment approval & release | B11: 5 | C11: 5 | D11: =IF(B11<3,"Manual/Kill",IF(AND(B11>=4,C11>=4),"Hybrid",IF(AND(B11>=4,C11<=3),"Automate","Hybrid"))) -> Hybrid | E11: Binding cash out; must gate above threshold

Sheet Value Model
A1: Annual value — target operating model vs naive full automation
B3: Recommended (Hybrid) | C3: Naive full automation
A4: Current manual labor cost | B4: =Assumptions!B4*Assumptions!B5*Assumptions!B7 -> 630000 | C4: =Assumptions!B4*Assumptions!B5*Assumptions!B7 -> 630000
A5: Target labor cost | B5: =(Assumptions!B4*Assumptions!B8*Assumptions!B11+Assumptions!B4*Assumptions!B9*Assumptions!B10)*Assumptions!B7 -> 81305 | C5: =Assumptions!B4*Assumptions!B8*Assumptions!B11*Assumptions!B7 -> 28385
A6: Labor saved | B6: =B4-B5 -> 548695 | C6: =C4-C5 -> 601615
A7: Duplicate losses prevented | B7: =Assumptions!B4*Assumptions!B17*Assumptions!B18*Assumptions!B19 -> 939600 | C7: =Assumptions!B4*Assumptions!B17*Assumptions!B18*Assumptions!B19 -> 939600
A8: Early-pay discount capture gain | B8: =Assumptions!B4*Assumptions!B22*Assumptions!B23*(Assumptions!B25-Assumptions!B24) -> 1944000 | C8: =Assumptions!B4*Assumptions!B22*Assumptions!B23*(Assumptions!B25-Assumptions!B24) -> 1944000
A9: Fraud losses incurred (cost) | B9: =0 -> 0 | C9: =-Assumptions!B4*Assumptions!B14*Assumptions!B15*Assumptions!B16 -> -3240000
A10: Cost to run | B10: =-SUM(Assumptions!B28:B30) -> -150000 | C10: =-SUM(Assumptions!B28:B30) -> -150000
A11: Net annual value | B11: =B6+B7+B8+B9+B10 -> 3282295 | C11: =C6+C7+C8+C9+C10 -> 95215
A13: Advantage of hybrid over full automation | B13: =B11-C11 -> 3187080
